

[
    {
        "id": 1,
        "type": "slider",
        "sliderThumb": [
            {
                "id": 1,
                "image": "img/photos/angermanagement1.png"
            },
            {
                "id": 2,
                "image": "img/photos/angermanagement2.jpg"
            }
        ],
        "icon": "icofont-brain",
        "title": "Anger Management",
        "excerpt": "Helping individuals understand, manage and cope with deep, anger related challenges.",
        "categories": ["Addiction Education", "Relapse Prevention", "Group Counseling", "One on One Therapy", "Job Training & Life Skills", "Virtual Therapy", "Prescription Drugs", "Temporary Housing Assistance"],
        "body": ["<p>By providing you with customized support and a professional setting that is safe and judge-free, Second Wind Rehabilitation Services aims to encourage and empower you to manage and cope with deep, anger related challenges. This support is facilitated through a combination of counseling services that assist you in understanding the root of your anger challenges so you can gain skills and apply techniques that balance your emotions and improve your relationships. </p>"],
        "priceList": [
            {
                "id": 1,
                "listTitle": "",
                "listArray": []
            },
            {
                "id": 2,
                "listTitle": "",
                "listArray": []
            }
        ]
    },
    {
        "id": 2,
        "type": "thumbnail",
        "media": {
            "thumb": "img/photos/communityoutreach1.png",
            "image": "img/photos/communityoutreach2.png"
        },
        "icon": "icofont-prescription",
        "title": "Second Wind Rehabilitation Program",
        "excerpt": "Supporting low-income and/or unhoused individuals by providing resources, essentials and professional guidance toward stability and overall wellbeing.",
        "categories": ["Addiction Education", "Relapse Prevention", "Group Counseling", "One on One Therapy", "Job Training & Life Skills", "Virtual Therapy", "Second Wind outreach", "Temporary Housing Assistance"],
        "body": ["<p>By providing professional services tailored specifically for low-income and/or unhoused individuals the Second Wind Outreach Program is dedicated to bridging the gap between your individualized economic stressors and a more stable, self-sufficient lifestyle. Through this program, you will be offered various resources that aid job training, shelter, mental health support and other essential needs. </p> "],
        "priceList": [
            {
                "id": 1,
                "listTitle": "",
                "listArray": []
            },
            {
                "id": 2,
                "listTitle": "",
                "listArray": []
            }
        ]
    },
    {
        "id": 3,
        "type": "thumbnail",
        "media": {
            "thumb": "img/photos/relapseprevention.png",
            "image": "img/photos/relapseprevention.png"
        },
        "icon": "icofont-heart-beat",
        "title": "Relapse Prevention",
        "excerpt": "Encouraging proactive strategies and coping mechanisms that prevent setbacks.",
        "categories": ["Addiction Education", "Relapse Prevention", "Group Counseling", "One on One Therapy", "Job Training & Life Skills", "Virtual Therapy", "Second Wind outreach", "Temporary Housing Assistance"],
        "body": ["<p>By providing you with the proper strategies, resources and support you need, Second Wind Rehabilitation Services aims to assist you in maintaining your sobriety and avoiding setbacks. Relapse prevention is facilitated through counseling services that provide understanding of individual triggers and negative coping mechanisms. After identifying past, current and potential stressors, our staff members are able to empower, educate and encourage you to develop a healthier lifestyle, proactive strategies and healthier coping mechanisms.</p>"],
        "priceList": [
            {
                "id": 1,
                "listTitle": "",
                "listArray": []
            },
            {
                "id": 2,
                "listTitle": "",
                "listArray": []
            }
        ]
    },
    {
        "id": 4,
        "type": "thumbnail",
        "media": {
            "thumb": "img/photos/grouptherapy.png",
            "image": "img/photos/grouptherapy.png"
        },
        "icon": "icofont-users-social",
        "title": "Group Counseling",
        "excerpt": "Professional counseling services designed to encourage healing in a safe, community style environment.",
        "categories": ["Addiction Education", "Relapse Prevention", "Group Counseling", "One on One Therapy", "Job Training & Life Skills", "Virtual Therapy", "Second Wind outreach", "Temporary Housing Assistance"],
        "body": ["<p>Providing you with a professional environment to gain self-awareness, share perspectives, explore similar experiences and overcome obstacles amongst peers allows Second Wind Rehabilitation Services to facilitate group counseling in a safe, non-judgemental and confidential space. Group counseling offers a combination of coummunity, therapy based exercises, resources and feedback that encourages growth, healing and reflection. </p>"],
        "priceList": [
            {
                "id": 1,
                "listTitle": "",
                "listArray": []
            },
            {
                "id": 2,
                "listTitle": "",
                "listArray": []
            }
        ]
    },
    {
        "id": 5,
        "type": "thumbnail",
        "media": {
            "thumb": "img/photos/singletherapy.png",
            "image": "img/photos/singletherapy.png"
        },
        "icon": "icofont-users-alt-4",
        "title": "One-on-One Counseling",
        "excerpt": "Professional counseling services designed to encourage healing in a safe, individualized environment.",
        "categories": ["Addiction Education", "Relapse Prevention", "Group Counseling", "One on One Therapy", "Job Training & Life Skills", "Virtual Therapy", "Second Wind outreach", "Temporary Housing Assistance"],
        "body": ["<p>Giving you a safe and confidential space to share your experiences, understand your challenges and develop coping strategies allows Second Wind Rehabilitation Services to provide treatment plans specific to your needs. One on One Counseling is designed to encourage you to explore your emotions and empower you to address challenges head on in order to achieve an overall healthier lifestyle.</p>"],
        "priceList": [
            {
                "id": 1,
                "listTitle": "",
                "listArray": []
            },
            {
                "id": 2,
                "listTitle": "",
                "listArray": []
            }
        ]
    },
    {
        "id": 6,
        "type": "thumbnail",
        "media": {
            "thumb": "img/photos/virtualtherapy.png",
            "image": "img/photos/virtualtherapy.png"
        },
        "icon": "icofont-live-support",
        "title": "Virtual Therapy",
        "excerpt": "Professional counseling services designed to encourage healing in a safe, virtual environment.",
        "categories": ["Addiction Education", "Relapse Prevention", "Group Counseling", "One on One Therapy", "Job Training & Life Skills", "Virtual Therapy", "Second Wind outreach", "Temporary Housing Assistance"],
        "body": ["<p>Ensuring that you have access to therapy services from the comfort of your home or a quiet location where you feel comfortable gives Second Wind Rehabilitation Services the ability to serve you without physical health or location constraints. Virtual therapy provides you with all of the same benefits as One on One Counseling with the goal of helping you achieve an overall healthier lifestyle.</p>"],
        "priceList": [
            {
                "id": 1,
                "listTitle": "",
                "listArray": []
            },
            {
                "id": 2,
                "listTitle": "",
                "listArray": []
            }
        ]
    },
    {
        "id": 7,
        "type": "thumbnail",
        "media": {
            "thumb": "img/photos/jobtraining.png",
            "image": "img/photos/jobtraining.png"
        },
        "icon": "icofont-search-job",
        "title": "Job Training & Life Skills",
        "excerpt": "Providing support and resources for practical job readiness, professional skill development and essential skills that encourage independence and adaptability.",
        "categories": ["Addiction Education", "Relapse Prevention", "Group Counseling", "One on One Therapy", "Job Training & Life Skills", "Virtual Therapy", "Second Wind outreach", "Temporary Housing Assistance"],
        "body": ["<p>Setting you up for success with practical job readiness, professional skill development and essential skills that encourage independence and adaptability. At Second Wind Rehabilitation Services, Job Training & Life Skills support provides you with the resources, encouragement and tools you need to transition into complete independence, a successful work-life as well as healthier and more fulfilling relationships.</p>"],
        "priceList": [
            {
                "id": 1,
                "listTitle": "",
                "listArray": []
            },
            {
                "id": 2,
                "listTitle": "",
                "listArray": []
            }
        ]
    },
    {
        "id": 8,
        "type": "thumbnail",
        "media": {
            "thumb": "img/photos/housing.png",
            "image": "img/photos/housing.png"
        },
        "icon": "icofont-home",
        "title": "Temporary Housing Assistance",
        "excerpt": "Providing short-term, safe, and sanitary housing assistance while you are in our care.",
        "categories": ["Addiction Education", "Relapse Prevention", "Group Counseling", "One on One Therapy", "Job Training & Life Skills", "Virtual Therapy", "Second Wind outreach", "Temporary Housing Assistance"],
        "body": ["<p>Providing you with a short-term, safe and sanitary living environment when you are in immediate need of housing assistance. With Second Wind Behavioral Health Centers, temporary housing assistance allows our staff to continue to aid in your specific mental health or substance abuse conditions while providing you with the resources, encouragement and essentials you need in order to rebuild stable, healthy and safe living conditions. </p>"],
        "priceList": [
            {
                "id": 1,
                "listTitle": "",
                "listArray": []
            },
            {
                "id": 2,
                "listTitle": "",
                "listArray": []
            }
        ]
    }
]